unitspec/__init__.py
unitspec/unitspec.py
unitspec-1.1.10.dist-info/DESCRIPTION.rst
unitspec-1.1.10.dist-info/METADATA
unitspec-1.1.10.dist-info/metadata.json
unitspec-1.1.10.dist-info/RECORD
unitspec-1.1.10.dist-info/top_level.txt
unitspec-1.1.10.dist-info/WHEEL
