Metadata-Version: 2.0
Name: unitspec
Version: 1.1.10
Summary: Specification tests within Python unittests
Home-page: https://github.com/Yegoroff/unitspec
Author: Alexander Yegorov
Author-email: UNKNOWN
License: MIT
Platform: UNKNOWN
